python/__init__.py
python/transform_server/__init__.py
python/transform_server/config_manager.py
python/transform_server/realtime_logger.py
python/transform_server/resource_providers_manager.py
python/transform_server/secrets_manager.py
python/transform_server/transform_server.py
python/transform_server/transform_server_as_lambda.py
python/transform_server/transformation_manager.py
tecton_core/__init__.py
tecton_core/id_helper.py
tecton_core/realtime_context.py
tecton_core/resource_provider_context.py
tecton_proto/__init__.py
tecton_proto/args/__init__.py
tecton_proto/args/basic_info__client_pb2.py
tecton_proto/args/basic_info__client_pb2.pyi
tecton_proto/args/data_source__client_pb2.py
tecton_proto/args/data_source__client_pb2.pyi
tecton_proto/args/data_source_config__client_pb2.py
tecton_proto/args/data_source_config__client_pb2.pyi
tecton_proto/args/diff_options__client_pb2.py
tecton_proto/args/diff_options__client_pb2.pyi
tecton_proto/args/diff_test__client_pb2.py
tecton_proto/args/diff_test__client_pb2.pyi
tecton_proto/args/entity__client_pb2.py
tecton_proto/args/entity__client_pb2.pyi
tecton_proto/args/fco_args__client_pb2.py
tecton_proto/args/fco_args__client_pb2.pyi
tecton_proto/args/feature_service__client_pb2.py
tecton_proto/args/feature_service__client_pb2.pyi
tecton_proto/args/feature_view__client_pb2.py
tecton_proto/args/feature_view__client_pb2.pyi
tecton_proto/args/pipeline__client_pb2.py
tecton_proto/args/pipeline__client_pb2.pyi
tecton_proto/args/repo_metadata__client_pb2.py
tecton_proto/args/repo_metadata__client_pb2.pyi
tecton_proto/args/resource_provider__client_pb2.py
tecton_proto/args/resource_provider__client_pb2.pyi
tecton_proto/args/server_group__client_pb2.py
tecton_proto/args/server_group__client_pb2.pyi
tecton_proto/args/transformation__client_pb2.py
tecton_proto/args/transformation__client_pb2.pyi
tecton_proto/args/user_defined_function__client_pb2.py
tecton_proto/args/user_defined_function__client_pb2.pyi
tecton_runtime-1.2.13.dist-info/METADATA
tecton_runtime-1.2.13.dist-info/WHEEL
tecton_runtime-1.2.13.dist-info/top_level.txt
tecton_runtime-1.2.13.dist-info/RECORD
