Metadata-Version: 2.1
Name: tecton_runtime
Version: 1.2.13
Summary: Tecton Transformation Service Sidecar
Home-page: https://tecton.ai
Author: Tecton, Inc.
Author-email: support@tecton.ai
License: Tecton Proprietary
Classifier: Programming Language :: Python :: 3
Classifier: Operating System :: OS Independent
Classifier: License :: Other/Proprietary License
Requires-Python: >=3.7
Requires-Dist: grpcio ==1.60.0
Requires-Dist: grpcio-reflection ==1.60.0
Requires-Dist: grpcio-health-checking ==1.60.0
Requires-Dist: numpy >=1.24.4
Requires-Dist: pandas >=1.3.5
Requires-Dist: pyarrow >=8.0.0
Requires-Dist: statsd >=3.3.0
Requires-Dist: psutil >=5.8.0
Requires-Dist: prometheus-client >=0.20.0
Requires-Dist: requests >=2.24
Requires-Dist: py-grpc-prometheus
Requires-Dist: boto3
Requires-Dist: readerwriterlock
Requires-Dist: schedule
Requires-Dist: attrs
